README.ja.md
outputdatareader/__init__.py
outputdatareader/readers.py
outputdatareader/scanners.py
outputdatareader-0.9.1.dist-info/LICENSE.txt
outputdatareader-0.9.1.dist-info/METADATA
outputdatareader-0.9.1.dist-info/WHEEL
outputdatareader-0.9.1.dist-info/RECORD
