Metadata-Version: 2.1
Name: outputdatareader
Version: 0.9.1
Summary: A reader for text file output from the program.
Home-page: https://github.com/takatoh/outputdatareader
License: MIT
Author: takatoh
Author-email: takatoh.m@gmail.com
Requires-Python: >=3.9,<4.0
Classifier: License :: OSI Approved :: MIT License
Classifier: Programming Language :: Python :: 3
Classifier: Programming Language :: Python :: 3.9
Classifier: Programming Language :: Python :: 3.10
Classifier: Programming Language :: Python :: 3.11
Classifier: Programming Language :: Python :: 3.12
Classifier: Programming Language :: Python :: 3.13
Project-URL: Repository, https://github.com/takatoh/outputdatareader
